setup.py
yqhouhello/hello.py
yqhoutest.egg-info/PKG-INFO
yqhoutest.egg-info/SOURCES.txt
yqhoutest.egg-info/dependency_links.txt
yqhoutest.egg-info/entry_points.txt
yqhoutest.egg-info/top_level.txt