Metadata-Version: 1.0
Name: yqhoutest
Version: 0.0.1
Summary: just for test
Home-page: http://gitlab.aibee.cn/ProductAnalysis/AutoTraining/tree/master/HotproductAutoTrain
Author: yqhou
Author-email: 1773054317@qq.com
License: GNU General Public License v3.0
Platform: UNKNOWN
